seesea/__init__.py
seesea/__main__.py
seesea/cli.py
seesea/browser/__init__.py
seesea/browser/base.py
seesea/browser/pool.py
seesea/browser/xinhua.py
seesea/embeddings/__init__.py
seesea/embeddings/manager.py
seesea/embeddings/pro.py
seesea/embeddings/simple.py
seesea/embeddings/standard.py
seesea/handlers/__init__.py
seesea/mcp/__init__.py
seesea/mcp/cleaner.py
seesea/mcp/hot.py
seesea/mcp/rss.py
seesea/mcp/search.py
seesea/mcp/stock.py
seesea/models/__init__.py
seesea/models/enums.py
seesea/models/exchange.py
seesea/models/stock.py
seesea/sdk/__init__.py
seesea/sdk/base/__init__.py
seesea/sdk/base/client.py
seesea/sdk/browser/__init__.py
seesea/sdk/browser/client.py
seesea/sdk/cache/__init__.py
seesea/sdk/cache/client.py
seesea/sdk/cleaner/__init__.py
seesea/sdk/cleaner/client.py
seesea/sdk/configuration/__init__.py
seesea/sdk/configuration/client.py
seesea/sdk/configuration/helper.py
seesea/sdk/date_page/__init__.py
seesea/sdk/date_page/client.py
seesea/sdk/embeddings/__init__.py
seesea/sdk/embeddings/callback.py
seesea/sdk/engines/__init__.py
seesea/sdk/engines/base.py
seesea/sdk/engines/examples.py
seesea/sdk/engines/manager.py
seesea/sdk/engines/registry.py
seesea/sdk/feed/__init__.py
seesea/sdk/feed/hot_client.py
seesea/sdk/feed/rss_client.py
seesea/sdk/net/__init__.py
seesea/sdk/net/client.py
seesea/sdk/search/__init__.py
seesea/sdk/search/client.py
seesea/sdk/seesea_types/__init__.py
seesea/sdk/seesea_types/api_types.py
seesea/sdk/seesea_types/cache_types.py
seesea/sdk/seesea_types/common_types.py
seesea/sdk/seesea_types/config_types.py
seesea/sdk/seesea_types/search_types.py
seesea/sdk/seesea_types/stock_types.py
seesea/sdk/seesea_types/vector_types.py
seesea/sdk/server/__init__.py
seesea/sdk/server/manager.py
seesea/sdk/stock/__init__.py
seesea/sdk/stock/client.py
seesea/sdk/stock/scheduler.py
seesea/sdk/vector/__init__.py
seesea/sdk/vector/client.py
seesea/utils/__init__.py
seesea/utils/formatters.py
seesea/utils/platform_paths.py
seesea-2.2.2.dist-info/METADATA
seesea-2.2.2.dist-info/WHEEL
seesea-2.2.2.dist-info/entry_points.txt
seesea-2.2.2.dist-info/top_level.txt
seesea-2.2.2.dist-info/RECORD
