Metadata-Version: 2.4
Name: seesea
Version: 2.2.2
Summary: SeeSea Python SDK - Privacy-focused metasearch engine
Author: nostalgiatan
License: AGPL-3.0-or-later
Project-URL: Homepage, https://github.com/nostalgiatan/SeeSea
Project-URL: Repository, https://github.com/nostalegan/SeeSea
Project-URL: Documentation, https://github.com/nostalegan/SeeSea/blob/main/docs
Keywords: search,metasearch,privacy,sdk
Classifier: Development Status :: 3 - Alpha
Classifier: Intended Audience :: Developers
Classifier: License :: OSI Approved :: GNU Affero General Public License v3 or later (AGPLv3+)
Classifier: Programming Language :: Python :: 3
Classifier: Programming Language :: Python :: 3.10
Classifier: Programming Language :: Python :: 3.11
Classifier: Programming Language :: Python :: 3.12
Classifier: Programming Language :: Python :: 3.13
Classifier: Programming Language :: Python :: 3.14
Classifier: Topic :: Internet :: WWW/HTTP :: Indexing/Search
Classifier: Topic :: Software Development :: Libraries :: Python Modules
Requires-Python: >=3.10
Requires-Dist: seesea-core>=2.0.4
Requires-Dist: psutil>=7.1.3
Requires-Dist: akshare>=1.15.0
Requires-Dist: pandas>=2.2.0
Requires-Dist: numpy>=2.0.0
Requires-Dist: pypinyin>=0.52.0
Provides-Extra: dev
Requires-Dist: pytest>=8.0; extra == "dev"
Requires-Dist: pytest-asyncio>=0.24; extra == "dev"
Requires-Dist: black>=24.0; extra == "dev"
Requires-Dist: mypy>=1.11; extra == "dev"
Requires-Dist: ruff>=0.8; extra == "dev"
Provides-Extra: mcp
Requires-Dist: fastmcp>=0.2.0; extra == "mcp"
